{
  "$schema": "../../node_modules/@openapitools/openapi-generator-cli/config.schema.json",
  "spaces": 2,
  "generator-cli": {
    "version": "6.1.0",
    "generators": {
      "challenge-user-service": {
        "generatorName": "spring",
        "output": "server",
        "inputSpec": "openapi.yaml",
        "templateDir": "templates",
        "additionalProperties": {
          "basePackage": "org.sagebionetworks.challenge",
          "apiPackage": "org.sagebionetworks.challenge.api",
          "modelPackage": "org.sagebionetworks.challenge.model.dto",
          "configPackage": "org.sagebionetworks.challenge.configuration",
          "delegatePattern": true
        }
      }
    }
  }
}
